[{"date":"Oct 3","active":4965,"resting":15295,"total":20260},{"date":"Oct 10","active":4957,"resting":15295,"total":20252},{"date":"Oct 17","active":2177,"resting":15295,"total":17472},{"date":"Oct 24","active":4982,"resting":15295,"total":20277},{"date":"Oct 31","active":2788,"resting":15295,"total":18083},{"date":"Nov 7","active":4818,"resting":15295,"total":20113},{"date":"Nov 14","active":8110,"resting":15295,"total":23405},{"date":"Nov 21","active":5033,"resting":15295,"total":20328},{"date":"Nov 28","active":4609,"resting":15295,"total":19904},{"date":"Dec 5","active":7117,"resting":15295,"total":22412},{"date":"Dec 12","active":7691,"resting":15295,"total":22986},{"date":"Dec 19","active":6709,"resting":15295,"total":22004},{"date":"Dec 26","active":487,"resting":15288,"total":15775},{"date":"Jan 2","active":8568,"resting":15246,"total":23814},{"date":"Jan 9","active":8674,"resting":15246,"total":23920},{"date":"Jan 16","active":4330,"resting":15246,"total":19576},{"date":"Jan 23","active":10898,"resting":15246,"total":26144},{"date":"Jan 30","active":10803,"resting":15246,"total":26049},{"date":"Feb 6","active":10751,"resting":15246,"total":25997},{"date":"Feb 13","active":5927,"resting":15246,"total":21173},{"date":"Feb 20","active":4199,"resting":7530,"total":11729},{"date":"Feb 27","active":476,"resting":2178,"total":2654},{"date":"Mar 6","active":9455,"resting":13068,"total":22523},{"date":"Mar 13","active":8707,"resting":15246,"total":23953},{"date":"Mar 20","active":10188,"resting":15246,"total":25434},{"date":"Mar 27","active":4533,"resting":6387,"total":10920},{"date":"Apr 3","active":667,"resting":0,"total":667},{"date":"Apr 10","active":10971,"resting":13068,"total":24039},{"date":"Apr 17","active":6106,"resting":15246,"total":21352},{"date":"Apr 24","active":11608,"resting":15246,"total":26854},{"date":"May 1","active":7462,"resting":15246,"total":22708},{"date":"May 8","active":12295,"resting":15246,"total":27541},{"date":"May 15","active":2702,"resting":5461,"total":8163},{"date":"May 22","active":4358,"resting":6534,"total":10892},{"date":"May 29","active":10746,"resting":15246,"total":25992},{"date":"Jun 5","active":10204,"resting":15246,"total":25450},{"date":"Jun 12","active":13772,"resting":15246,"total":29018},{"date":"Jun 19","active":10553,"resting":15246,"total":25799},{"date":"Jun 26","active":6643,"resting":14831,"total":21474},{"date":"Jul 3","active":8190,"resting":15246,"total":23436},{"date":"Jul 10","active":5740,"resting":15246,"total":20986},{"date":"Jul 17","active":11997,"resting":15246,"total":27243},{"date":"Jul 24","active":8162,"resting":15246,"total":23408},{"date":"Jul 31","active":613,"resting":15246,"total":15859},{"date":"Aug 7","active":10038,"resting":15246,"total":25284},{"date":"Aug 14","active":13311,"resting":14166,"total":27477},{"date":"Aug 21","active":11307,"resting":13068,"total":24375},{"date":"Aug 28","active":5338,"resting":15246,"total":20584},{"date":"Sep 4","active":7413,"resting":15246,"total":22659},{"date":"Sep 11","active":12155,"resting":15246,"total":27401},{"date":"Sep 18","active":11415,"resting":15246,"total":26661},{"date":"Sep 25","active":2524,"resting":6602,"total":9126}]